DongshouXueShenduXuexiPytorchBan2020313/README.md
DongshouXueShenduXuexiPytorchBan2020313/__init__.py
DongshouXueShenduXuexiPytorchBan2020313/__main__.py
DongshouXueShenduXuexiPytorchBan2020313/file.epub
DongshouXueShenduXuexiPytorchBan2020313/index.html
DongshouXueShenduXuexiPytorchBan2020313/css/__init__.py
DongshouXueShenduXuexiPytorchBan2020313/css/annotations.css
DongshouXueShenduXuexiPytorchBan2020313/css/main.css
DongshouXueShenduXuexiPytorchBan2020313/css/normalize.css
DongshouXueShenduXuexiPytorchBan2020313/css/popup.css
DongshouXueShenduXuexiPytorchBan2020313/font/__init__.py
DongshouXueShenduXuexiPytorchBan2020313/font/fontello.eot
DongshouXueShenduXuexiPytorchBan2020313/font/fontello.svg
DongshouXueShenduXuexiPytorchBan2020313/font/fontello.ttf
DongshouXueShenduXuexiPytorchBan2020313/font/fontello.woff
DongshouXueShenduXuexiPytorchBan2020313/img/__init__.py
DongshouXueShenduXuexiPytorchBan2020313/img/annotator-glyph-sprite.png
DongshouXueShenduXuexiPytorchBan2020313/img/annotator-icon-sprite.png
DongshouXueShenduXuexiPytorchBan2020313/img/apple-touch-icon.png
DongshouXueShenduXuexiPytorchBan2020313/img/cancelfullscreen.png
DongshouXueShenduXuexiPytorchBan2020313/img/close.png
DongshouXueShenduXuexiPytorchBan2020313/img/fullscreen.png
DongshouXueShenduXuexiPytorchBan2020313/img/loader.gif
DongshouXueShenduXuexiPytorchBan2020313/img/menu-icon.png
DongshouXueShenduXuexiPytorchBan2020313/img/save.png
DongshouXueShenduXuexiPytorchBan2020313/img/saved.png
DongshouXueShenduXuexiPytorchBan2020313/img/settings-s.png
DongshouXueShenduXuexiPytorchBan2020313/img/settings.png
DongshouXueShenduXuexiPytorchBan2020313/img/star.png
DongshouXueShenduXuexiPytorchBan2020313/js/__init__.py
DongshouXueShenduXuexiPytorchBan2020313/js/epub.js
DongshouXueShenduXuexiPytorchBan2020313/js/epub.min.js
DongshouXueShenduXuexiPytorchBan2020313/js/epub.min.map
DongshouXueShenduXuexiPytorchBan2020313/js/hooks.min.js
DongshouXueShenduXuexiPytorchBan2020313/js/hooks.min.map
dongshou_xue_shendu_xuexi_pytorch_ban_2020_3_13-2024.3.5.0.dist-info/METADATA
dongshou_xue_shendu_xuexi_pytorch_ban_2020_3_13-2024.3.5.0.dist-info/WHEEL
dongshou_xue_shendu_xuexi_pytorch_ban_2020_3_13-2024.3.5.0.dist-info/entry_points.txt
dongshou_xue_shendu_xuexi_pytorch_ban_2020_3_13-2024.3.5.0.dist-info/top_level.txt
dongshou_xue_shendu_xuexi_pytorch_ban_2020_3_13-2024.3.5.0.dist-info/RECORD
